log/__init__.py
log/admin.py
log/apps.py
log/models.py
log/tests.py
log/urls.py
log/utils.py
log/views.py
log/migrations/0001_initial.py
log/migrations/0002_auto_20230223_0929.py
log/migrations/0003_auto_20230223_1048.py
log/migrations/0004_log_priv_address.py
log/migrations/0005_log_hashed.py
log/migrations/0006_log_device.py
log/migrations/0007_log_ip_type.py
log/migrations/0008_alter_log_ip_type.py
log/migrations/0009_rename_ip_type_log_is_private.py
log/migrations/__init__.py
log/migrations/__pycache__/0001_initial.cpython-310.pyc
log/migrations/__pycache__/0002_auto_20230223_0929.cpython-310.pyc
log/migrations/__pycache__/0003_auto_20230223_1048.cpython-310.pyc
log/migrations/__pycache__/0004_log_priv_address.cpython-310.pyc
log/migrations/__pycache__/0005_log_hashed.cpython-310.pyc
log/migrations/__pycache__/0006_log_device.cpython-310.pyc
log/migrations/__pycache__/0007_log_ip_type.cpython-310.pyc
log/migrations/__pycache__/0008_alter_log_ip_type.cpython-310.pyc
log/migrations/__pycache__/0009_rename_ip_type_log_is_private.cpython-310.pyc
log/migrations/__pycache__/__init__.cpython-310.pyc
log/templates/log/detail.html
log/templates/log/list.html
django_ipghrms_log-1.13.dist-info/LICENSE
django_ipghrms_log-1.13.dist-info/METADATA
django_ipghrms_log-1.13.dist-info/WHEEL
django_ipghrms_log-1.13.dist-info/top_level.txt
django_ipghrms_log-1.13.dist-info/RECORD
